alfred/__init__.py
alfred/cocoa.py
alfred-0.3.dist-info/LICENSE.txt
alfred-0.3.dist-info/METADATA
alfred-0.3.dist-info/WHEEL
alfred-0.3.dist-info/top_level.txt
alfred-0.3.dist-info/RECORD
